{"query_id":"447399","query_title":"X-Men: The Mutant Watch","recommendations":[{"id":"239459","title":"No Half Measures: Creating the Final Season of Breaking Bad","year":2013,"genres":"Documentary","poster":"/ApitDfnYDwFNOPfyVuhW5ElWzhe.jpg","rating":8.4,"overview":"A documentary about the making of season five of the acclaimed AMC series Breaking Bad.","hybrid_score":0.8883,"director":"Stuart Richardson"},{"id":"455565","title":"Bombshell: The Hedy Lamarr Story","year":2018,"genres":"Documentary","poster":"/7kZonXfPuXZzwZIu9f7YPQmFXWQ.jpg","rating":6.9,"overview":"The life and career of the hailed Hollywood movie star and underappreciated genius inventor, Hedy Lamarr.","hybrid_score":0.7149,"director":"Alexandra Dean"},{"id":"241829","title":"The Making of The Walking Dead","year":2010,"genres":"Documentary","poster":"/8V7FDbfxqgA6rKTEYOKpgeORPFV.jpg","rating":7.9,"overview":"The Making of the TV Series The Walking Dead.","hybrid_score":0.7072,"director":"Constantine Nasr"},{"id":"63404","title":"American Pie: Revealed","year":2004,"genres":"Documentary, Comedy","poster":"/zd6vScAUAp3blRMa2ZCsFY2SUNk.jpg","rating":6.0,"overview":"Documentary about the making of American Pie (1999), American Pie 2 (2001) and American Wedding (2003).","hybrid_score":0.4887,"director":"Dave McVeigh, Scott McVeigh"},{"id":"40819","title":"Best Worst Movie","year":2009,"genres":"Documentary, Comedy","poster":"/4LQ6kdvVJW9y0B9O4qDTsazNzER.jpg","rating":7.1,"overview":"A look at the making of the film Troll 2 (1990) and its journey from being crowned the \"worst film of all time\" to a cherished cult classic.","hybrid_score":0.4827,"director":"Michael Stephenson"},{"id":"569543","title":"Mia Martini - I Am Mia","year":2019,"genres":"History, Documentary, Music","poster":"/uAZMY2je5PSoLrjvMLBZanKGXca.jpg","rating":7.2,"overview":"The movie is a biopic about Mia Martini, an italian singer who died in 1995.","hybrid_score":0.4816,"director":"Riccardo Donna"},{"id":"609797","title":"Wandering Stars","year":2019,"genres":"Documentary, Music","poster":"/q9fp9guKgImiJPhkeZL6cBRLH5z.jpg","rating":7.4,"overview":"This film follows the making of Nekfeu's 3rd album, between Paris, Japan, Greece and the United States.","hybrid_score":0.4809,"director":"Nekfeu, Syrine Boulanouar"},{"id":"953300","title":"The Mystery of Marilyn Monroe: The Unheard Tapes","year":2022,"genres":"Documentary","poster":"/9Ab3MEngH2sWK8uydGBFfgZDB4z.jpg","rating":6.3,"overview":"This documentary explores the mystery surrounding the death of movie icon Marilyn Monroe through previously unheard interviews with her inner circle.","hybrid_score":0.4466,"director":"Emma Cooper"},{"id":"14543","title":"The Matrix Revisited","year":2001,"genres":"Documentary","poster":"/8yxSztoc5sqZiGuKcFuVOh65B6Y.jpg","rating":6.8,"overview":"The film goes behind the scenes of the 1999 sci-fi movie The Matrix.","hybrid_score":0.4452,"director":"Josh Oreck"},{"id":"656690","title":"The Social Dilemma","year":2020,"genres":"Documentary, Drama","poster":"/jcaM6V2tCtu6iMHDsGLBUbaYgYp.jpg","rating":7.5,"overview":"This documentary-drama hybrid explores the dangerous human impact of social networking, with tech experts sounding the alarm on their own creations.","hybrid_score":0.4223,"director":"Jeff Orlowski"}]}